parse_slice.py
parse_slice-0.1.0a1.dist-info/licenses/LICENSE
parse_slice-0.1.0a1.dist-info/METADATA
parse_slice-0.1.0a1.dist-info/WHEEL
parse_slice-0.1.0a1.dist-info/top_level.txt
parse_slice-0.1.0a1.dist-info/RECORD
