Metadata-Version: 2.4
Name: parse-slice
Version: 0.1.0a1
Summary: A Python function that normalizes and validates slice objects, ensuring correct bounds based on the step direction.
Author-email: Jifeng Wu <jifengwu2k@gmail.com>
License-Expression: MIT
Project-URL: Homepage, https://github.com/jifengwu2k/parse-slice
Project-URL: Bug Tracker, https://github.com/jifengwu2k/parse-slice/issues
Classifier: Programming Language :: Python :: 2
Classifier: Programming Language :: Python :: 3
Classifier: Operating System :: OS Independent
Requires-Python: >=2
License-File: LICENSE
Dynamic: license-file
